shipami/__init__.py
shipami/cli.py
shipami/core.py
shipami-1.1.0.dist-info/DESCRIPTION.rst
shipami-1.1.0.dist-info/METADATA
shipami-1.1.0.dist-info/RECORD
shipami-1.1.0.dist-info/WHEEL
shipami-1.1.0.dist-info/entry_points.txt
shipami-1.1.0.dist-info/metadata.json
shipami-1.1.0.dist-info/top_level.txt
