Metadata-Version: 2.0
Name: shipami
Version: 1.1.0
Summary: CLI tool to manage AWS AMI and Marketplace
Home-page: http://github.com/wnkz/shipami
Author: wnkz
Author-email: wnkz@users.noreply.github.com
License: MIT
Download-URL: https://github.com/wnkz/shipami/archive/1.1.0.tar.gz
Keywords: aws ec2 ami marketplace
Platform: UNKNOWN
Classifier: Development Status :: 3 - Alpha
Classifier: Intended Audience :: Developers
Classifier: Intended Audience :: System Administrators
Classifier: License :: OSI Approved :: MIT License
Classifier: Programming Language :: Python :: 2
Classifier: Programming Language :: Python :: 2.6
Classifier: Programming Language :: Python :: 2.7
Classifier: Programming Language :: Python :: 3
Classifier: Programming Language :: Python :: 3.3
Classifier: Programming Language :: Python :: 3.4
Classifier: Programming Language :: Python :: 3.5
Requires-Dist: click (==6.7)
Requires-Dist: boto3 (>=1.4.4)
Requires-Dist: tabulate (>=0.7.7)
Requires-Dist: timeago (>=1.0.7)
